HISTORY.rst
LICENSE.txt
MANIFEST.in
README.rst
dev-requirements.txt
requirements.txt
setup.py
flotsam/__init__.py
flotsam/collection_util.py
flotsam/file_util.py
flotsam/pytest_util.py
flotsam.egg-info/PKG-INFO
flotsam.egg-info/SOURCES.txt
flotsam.egg-info/dependency_links.txt
flotsam.egg-info/not-zip-safe
flotsam.egg-info/requires.txt
flotsam.egg-info/top_level.txt
tests/__init__.py
tests/collection_util_test.py
tests/conftest.py
tests/file_util_test.py