Metadata-Version: 1.1
Name: flotsam
Version: 0.1.0
Summary: Miscellaneous utilities
Home-page: biskup-software.de
Author: Bernhard (Bernd) Biskup
Author-email: bbiskup@gmx.de
License: The MIT License (MIT)
Keywords: flotsam utilities
Platform: UNKNOWN
Classifier: Development Status :: 2 - Pre-Alpha
Classifier: Environment :: Console
Classifier: Intended Audience :: Developers
Classifier: License :: OSI Approved :: MIT License
Classifier: Programming Language :: Python :: 2.7
Classifier: Programming Language :: Python :: 3.4
